LICENSE
MANIFEST.in
README.md
setup.cfg
setup.py
versioneer.py
./.gitattributes
./CODE_OF_CONDUCT.md
./CONTRIBUTING.md
./LICENSE
./MANIFEST.in
./README.md
./setup.cfg
./setup.py
./versioneer.py
./adparallelengine/__init__.py
./adparallelengine/_version.py
./adparallelengine/adparallelengine.py
./adparallelengine/decorators.py
./adparallelengine.egg-info/PKG-INFO
./adparallelengine.egg-info/SOURCES.txt
./adparallelengine.egg-info/dependency_links.txt
./adparallelengine.egg-info/requires.txt
./adparallelengine.egg-info/top_level.txt
./tests/__init__.py
./tests/main.py
./tests/test_adengine.py
adparallelengine/__init__.py
adparallelengine/_version.py
adparallelengine/adparallelengine.py
adparallelengine/decorators.py
adparallelengine.egg-info/PKG-INFO
adparallelengine.egg-info/SOURCES.txt
adparallelengine.egg-info/dependency_links.txt
adparallelengine.egg-info/requires.txt
adparallelengine.egg-info/top_level.txt
tests/__init__.py
tests/main.py
tests/test_adengine.py