Metadata-Version: 2.1
Name: adparallelengine
Version: 0.1.22
Summary: A wrapper around several ways of doing map multiprocessing in Python
Home-page: https://github.com/Advestis/adparallelengine
Author: Advestis
Author-email: pythondev@advestis.com
License: GPLv3
Project-URL: Bug Tracker, https://github.com/Advestis/adparallelengine/issues
Project-URL: Documentation, https://advestis.github.io/adparallelengine
Project-URL: Source Code, https://github.com/Advestis/adparallelengine/
Platform: UNKNOWN
Classifier: Development Status :: 5 - Production/Stable
Classifier: License :: OSI Approved :: GNU General Public License v3 (GPLv3)
Classifier: Operating System :: Unix
Classifier: Programming Language :: Python :: 3.7
Classifier: Programming Language :: Python :: 3.8
Classifier: Programming Language :: Python :: 3.9
Requires-Python: >=3.7
Provides-Extra: dask
Provides-Extra: k8s
Provides-Extra: mpi
Provides-Extra: support_shared
Provides-Extra: all
License-File: LICENSE
